observable_properties.py
observable_properties-4.0.0.dist-info/LICENSE
observable_properties-4.0.0.dist-info/METADATA
observable_properties-4.0.0.dist-info/WHEEL
observable_properties-4.0.0.dist-info/top_level.txt
observable_properties-4.0.0.dist-info/RECORD
