Metadata-Version: 2.1
Name: observable-properties
Version: 4.0.0
Summary: Observable managed attributes (aka, observable properties)
Author: Ángel Fernández Pineda
License: EUROPEAN UNION PUBLIC LICENCE v. 1.2
Project-URL: Homepage, https://github.com/afpineda/observable-properties-python
Keywords: observable,managed attributes,properties
Classifier: Programming Language :: Python :: 3.11
Classifier: Intended Audience :: Developers
Classifier: Operating System :: OS Independent
Classifier: License :: OSI Approved :: European Union Public Licence 1.2 (EUPL 1.2)
Requires-Python: >=3.11
License-File: LICENSE
